icoshift3/__init__.py
icoshift3/icoshift.py
icoshift3/test_wine.py
icoshift3/tests.py
icoshift3-0.0.3.dist-info/COPYING
icoshift3-0.0.3.dist-info/LICENSE
icoshift3-0.0.3.dist-info/METADATA
icoshift3-0.0.3.dist-info/WHEEL
icoshift3-0.0.3.dist-info/top_level.txt
icoshift3-0.0.3.dist-info/RECORD
