Metadata-Version: 2.1
Name: icoshift3
Version: 0.0.3
Summary: Spectral Icoshift updated for python v.3
Home-page: https://github.com/JonWestern/icoshift3.git
Author: Charley Western
Author-email: westernj@lafayette.edu
License: GPL
Keywords: bioinformatics metabolomics research analysis science
Platform: UNKNOWN
Classifier: Development Status :: 4 - Beta
Classifier: Natural Language :: English
Classifier: Operating System :: OS Independent
Classifier: Programming Language :: Python :: 2
Classifier: License :: OSI Approved :: BSD License
Classifier: Topic :: Scientific/Engineering :: Bio-Informatics
Classifier: Intended Audience :: Science/Research
Classifier: Intended Audience :: Education
Requires-Python: >=3.0
Requires-Dist: numpy (>=1.7.1)
Requires-Dist: scipy (>=0.12.0)
